package_logger/package_logger.py
package_logger-1.0.0.dist-info/METADATA
package_logger-1.0.0.dist-info/WHEEL
package_logger-1.0.0.dist-info/top_level.txt
package_logger-1.0.0.dist-info/RECORD
