Metadata-Version: 2.1
Name: package-logger
Version: 1.0.0
Summary: Logger for Python
Home-page: https://github.com/sachin-acharya-projects/package_logger
Author: Sachin Acharya
Author-email: acharyaraj71+logger@gmail.com
Keywords: python3-logger logger debugging print
Classifier: Programming Language :: Python :: 3
Classifier: License :: OSI Approved :: MIT License
Classifier: Operating System :: OS Independent
Requires-Dist: colorama
